ceilometer_fiprom/__init__.py
ceilometer_fiprom/fiprom_publisher.py
ceilometer_fiprom/fiprom_storage.py
ceilometer_fiprom/metric_enrichment.py
ceilometer_fiprom/prom_metric.py
ceilometer_fiprom/util.py
fiware_prometheus_publisher-0.0.40.dist-info/LICENSE
fiware_prometheus_publisher-0.0.40.dist-info/METADATA
fiware_prometheus_publisher-0.0.40.dist-info/WHEEL
fiware_prometheus_publisher-0.0.40.dist-info/entry_points.txt
fiware_prometheus_publisher-0.0.40.dist-info/top_level.txt
fiware_prometheus_publisher-0.0.40.dist-info/RECORD
