Metadata-Version: 2.1
Name: fiware-prometheus-publisher
Version: 0.0.40
Summary: Ceilometer Publisher for the FIWARE infrastructure
Home-page: https://github.com/gabrielegiammatteo/fiware-prometheus-publisher
Author: Gabriele Giammatteo
Author-email: gabriele.giammatteo@eng.it
License: UNKNOWN
Keywords: monitoring ceilometer FIWARE metrics
Platform: UNKNOWN
Classifier: Development Status :: 3 - Alpha
Classifier: Intended Audience :: Developers
Classifier: Topic :: System :: Monitoring
Classifier: License :: OSI Approved :: Apache Software License
Classifier: Programming Language :: Python :: 2.7
Requires-Python: <3
